{
    "1992": [
        { "number": "1", "name": "Bodo Illgner" },
        { "number": "2", "name": "Stefan Reuter" },
        { "number": "3", "name": "Andreas Brehme" },
        { "number": "4", "name": "Jürgen Kohler" },
        { "number": "5", "name": "Manfred Binz" },
        { "number": "6", "name": "Guido Buchwald" },
        { "number": "7", "name": "Andreas Möller" },
        { "number": "8", "name": "Thomas Häßler" },
        { "number": "9", "name": "Rudi Völler" },
        { "number": "10", "name": "Thomas Doll" },
        { "number": "11", "name": "Karl-Heinz Riedle" },
        { "number": "12", "name": "Andreas Köpke" },
        { "number": "13", "name": "Andreas Thom" },
        { "number": "14", "name": "Thomas Helmer" },
        { "number": "15", "name": "Michael Frontzeck" },
        { "number": "16", "name": "Matthias Sammer" },
        { "number": "17", "name": "Stefan Effenberg" },
        { "number": "18", "name": "Jürgen Klinsmann" },
        { "number": "19", "name": "Michael Schulz" },
        { "number": "20", "name": "Christian Wörns" }
    ],
    "1996": [
        { "number": "1", "name": "Andreas Köpke" },
        { "number": "2", "name": "Thomas Helmer" },
        { "number": "3", "name": "Stefan Reuter" },
        { "number": "4", "name": "Jürgen Kohler" },
        { "number": "5", "name": "Thomas Häßler" },
        { "number": "6", "name": "Matthias Sammer" },
        { "number": "7", "name": "Andy Möller" },
        { "number": "8", "name": "Mehmet Scholl" },
        { "number": "9", "name": "Oliver Bierhoff" },
        { "number": "10", "name": "Thomas Strunz" },
        { "number": "11", "name": "Jürgen Klinsmann" },
        { "number": "12", "name": "Oliver Kahn" },
        { "number": "13", "name": "Dietmar Hamann" },
        { "number": "14", "name": "Christian Ziege" },
        { "number": "15", "name": "Steffen Freund" },
        { "number": "16", "name": "Markus Babbel" },
        { "number": "17", "name": "Fredi Bobic" },
        { "number": "18", "name": "Mario Basler" },
        { "number": "19", "name": "René Schneider" },
        { "number": "20", "name": "Marco Bode" },
        { "number": "21", "name": "Jens Todt" },
        { "number": "22", "name": "Ulf Kirsten" }
    ],
    "2000": [
        { "number": "1", "name": "Oliver Kahn" },
        { "number": "2", "name": "Markus Babbel" },
        { "number": "3", "name": "Michael Tarnat" },
        { "number": "4", "name": "Marko Rehmer" },
        { "number": "5", "name": "Jens Nowotny" },
        { "number": "6", "name": "Dieter Hamann" },
        { "number": "7", "name": "Thomas Häßler" },
        { "number": "8", "name": "Carsten Jancker" },
        { "number": "9", "name": "Ulf Kirsten" },
        { "number": "10", "name": "Lothar Matthäus" },
        { "number": "11", "name": "Oliver Bierhoff" },
        { "number": "12", "name": "Jörg Heinrich" },
        { "number": "13", "name": "Sebastian Deisler" },
        { "number": "14", "name": "Christian Ziege" },
        { "number": "15", "name": "Paulo Rink" },
        { "number": "16", "name": "Lars Ricken" },
        { "number": "17", "name": "Marco Bode" },
        { "number": "18", "name": "Mehmet Scholl" },
        { "number": "19", "name": "Markus Münch" },
        { "number": "20", "name": "Jens Lehmann" },
        { "number": "21", "name": "Michael Preetz" },
        { "number": "22", "name": "Oliver Neuville" }
    ],
    "2004": [
        { "number": "1", "name": "Oliver Kahn" },
        { "number": "2", "name": "Frank Baumann" },
        { "number": "3", "name": "Arne Friedrich" },
        { "number": "4", "name": "Jens Nowotny" },
        { "number": "5", "name": "Christian Wörns" },
        { "number": "6", "name": "Paul Freier" },
        { "number": "7", "name": "Torsten Frings" },
        { "number": "8", "name": "Dietmar Hamann" },
        { "number": "9", "name": "Carsten Ramelow" },
        { "number": "10", "name": "Michael Ballack" },
        { "number": "11", "name": "Kevin Kuranyi" },
        { "number": "12", "name": "Jens Lehmann" },
        { "number": "13", "name": "Sebastian Kehl" },
        { "number": "14", "name": "Philipp Lahm" },
        { "number": "15", "name": "Thomas Brdaric" },
        { "number": "16", "name": "Bastian Schweinsteiger" },
        { "number": "17", "name": "Bernd Schneider" },
        { "number": "18", "name": "Miroslav Klose" },
        { "number": "19", "name": "Fabian Ernst" },
        { "number": "20", "name": "Christian Ziege" },
        { "number": "21", "name": "Arne Friedrich" },
        { "number": "22", "name": "Timo Hildebrand" }
    ],
    "2008": [
        { "number": "1", "name": "Jens Lehmann" },
        { "number": "2", "name": "Marcell Jansen" },
        { "number": "3", "name": "Arne Friedrich" },
        { "number": "4", "name": "Clemens Fritz" },
        { "number": "5", "name": "Heiko Westermann" },
        { "number": "6", "name": "Simon Rolfes" },
        { "number": "7", "name": "Bastian Schweinsteiger" },
        { "number": "8", "name": "Torsten Frings" },
        { "number": "9", "name": "Mario Gómez" },
        { "number": "10", "name": "Oliver Neuville" },
        { "number": "11", "name": "Miroslav Klose" },
        { "number": "12", "name": "Robert Enke" },
        { "number": "13", "name": "Michael Ballack" },
        { "number": "14", "name": "Piotr Trochowski" },
        { "number": "15", "name": "Thomas Hitzlsperger" },
        { "number": "16", "name": "Philipp Lahm" },
        { "number": "17", "name": "Per Mertesacker" },
        { "number": "18", "name": "Tim Borowski" },
        { "number": "19", "name": "Lukas Podolski" },
        { "number": "20", "name": "Jérôme Boateng" },
        { "number": "21", "name": "René Adler" },
        { "number": "22", "name": "Andreas Beck" }
    ],
    "2012": [
        { "number": "1", "name": "Manuel Neuer" },
        { "number": "2", "name": "Marcel Schmelzer" },
        { "number": "3", "name": "Per Mertesacker" },
        { "number": "4", "name": "Holger Badstuber" },
        { "number": "5", "name": "Mats Hummels" },
        { "number": "6", "name": "Sami Khedira" },
        { "number": "7", "name": "Bastian Schweinsteiger" },
        { "number": "8", "name": "Mesut Özil" },
        { "number": "9", "name": "André Schürrle" },
        { "number": "10", "name": "Lukas Podolski" },
        { "number": "11", "name": "Miroslav Klose" },
        { "number": "12", "name": "Tim Wiese" },
        { "number": "13", "name": "Thomas Müller" },
        { "number": "14", "name": "Holger Badstuber" },
        { "number": "15", "name": "Christian Träsch" },
        { "number": "16", "name": "Philipp Lahm" },
        { "number": "17", "name": "Mats Hummels" },
        { "number": "18", "name": "Toni Kroos" },
        { "number": "19", "name": "Mario Götze" },
        { "number": "20", "name": "Mario Gomez" },
        { "number": "21", "name": "Benedikt Höwedes" },
        { "number": "22", "name": "Ron-Robert Zieler" }
    ],
    "2016": [
        { "number": "1", "name": "Manuel Neuer" },
        { "number": "2", "name": "Shkodran Mustafi" },
        { "number": "3", "name": "Jonas Hector" },
        { "number": "4", "name": "Benedikt Höwedes" },
        { "number": "5", "name": "Mats Hummels" },
        { "number": "6", "name": "Sami Khedira" },
        { "number": "7", "name": "Bastian Schweinsteiger" },
        { "number": "8", "name": "Mesut Özil" },
        { "number": "9", "name": "André Schürrle" },
        { "number": "10", "name": "Lukas Podolski" },
        { "number": "11", "name": "Julian Draxler" },
        { "number": "12", "name": "Bernd Leno" },
        { "number": "13", "name": "Thomas Müller" },
        { "number": "14", "name": "Emre Can" },
        { "number": "15", "name": "Julian Weigl" },
        { "number": "16", "name": "Joshua Kimmich" },
        { "number": "17", "name": "Jérôme Boateng" },
        { "number": "18", "name": "Toni Kroos" },
        { "number": "19", "name": "Leroy Sané" },
        { "number": "20", "name": "Mario Gomez" },
        { "number": "21", "name": "Joshua Kimmich" },
        { "number": "22", "name": "Kevin Trapp" },
        { "number": "23", "name": "Mario Götze" }
    ],
    "2020": [
        { "number": "1", "name": "Manuel Neuer" },
        { "number": "2", "name": "Antonio Rüdiger" },
        { "number": "3", "name": "Marcel Halstenberg" },
        { "number": "4", "name": "Matthias Ginter" },
        { "number": "5", "name": "Jonathan Tah" },
        { "number": "6", "name": "Joshua Kimmich" },
        { "number": "7", "name": "Kai Havertz" },
        { "number": "8", "name": "Toni Kroos" },
        { "number": "9", "name": "Leroy Sané" },
        { "number": "10", "name": "Serge Gnabry" },
        { "number": "11", "name": "Timo Werner" },
        { "number": "12", "name": "Bernd Leno" },
        { "number": "13", "name": "Lukas Klostermann" },
        { "number": "14", "name": "Leon Goretzka" },
        { "number": "15", "name": "Niklas Süle" },
        { "number": "16", "name": "Robin Koch" },
        { "number": "17", "name": "Emre Can" },
        { "number": "18", "name": "Florian Neuhaus" },
        { "number": "19", "name": "Luca Waldschmidt" },
        { "number": "20", "name": "Julian Brandt" },
        { "number": "21", "name": "Ilkay Gündogan" },
        { "number": "22", "name": "Kevin Trapp" },
        { "number": "23", "name": "Kevin Volland" }
    ]
}
